{"chunk_definitions":[{"row":31,"row_count":1,"visible":true,"expansion_state":0,"options":{"engine":"r","label":"setup","include":false},"document_id":"933E5A60","chunk_id":"csetup_chunk","chunk_label":"setup"},{"row":62,"row_count":1,"visible":true,"expansion_state":0,"options":{"engine":"r","label":"unnamed-chunk-57"},"document_id":"933E5A60","chunk_id":"c8p6qkyhe79hc","chunk_label":"unnamed-chunk-1"},{"row":79,"row_count":1,"visible":true,"expansion_state":0,"options":{"engine":"r","label":"unnamed-chunk-60"},"document_id":"933E5A60","chunk_id":"cyf0c6rr7unks","chunk_label":"unnamed-chunk-2"},{"row":98,"row_count":1,"visible":true,"expansion_state":0,"options":{"engine":"r","label":"unnamed-chunk-61"},"document_id":"933E5A60","chunk_id":"clhy5axrqetf7","chunk_label":"unnamed-chunk-3"},{"row":116,"row_count":1,"visible":true,"expansion_state":0,"options":{"engine":"r","label":"unnamed-chunk-64"},"document_id":"933E5A60","chunk_id":"cc6oq3kgvk42p","chunk_label":"unnamed-chunk-4"},{"row":134,"row_count":1,"visible":true,"expansion_state":0,"options":{"engine":"r","label":"unnamed-chunk-65"},"document_id":"933E5A60","chunk_id":"c2e2dkqgz8xhk","chunk_label":"unnamed-chunk-5"},{"row":141,"row_count":1,"visible":true,"expansion_state":0,"options":{"engine":"r","label":"unnamed-chunk-68"},"document_id":"933E5A60","chunk_id":"c85xs4p9r13l0","chunk_label":"unnamed-chunk-6"},{"row":153,"row_count":1,"visible":true,"expansion_state":0,"options":{"engine":"r","label":"unnamed-chunk-70"},"document_id":"933E5A60","chunk_id":"clg4a1r39f1y9","chunk_label":"unnamed-chunk-7"},{"row":164,"row_count":1,"visible":true,"expansion_state":0,"options":{"engine":"r","label":"unnamed-chunk-71"},"document_id":"933E5A60","chunk_id":"cm51aoq59mfj1","chunk_label":"unnamed-chunk-8"},{"row":175,"row_count":1,"visible":true,"expansion_state":0,"options":{"engine":"r","label":"unnamed-chunk-72"},"document_id":"933E5A60","chunk_id":"clv3e825n3sds","chunk_label":"unnamed-chunk-9"},{"row":185,"row_count":1,"visible":true,"expansion_state":0,"options":{"engine":"r","label":"unnamed-chunk-74"},"document_id":"933E5A60","chunk_id":"cgcx9alh6un4r","chunk_label":"unnamed-chunk-10"},{"row":289,"row_count":1,"visible":true,"expansion_state":0,"options":{"engine":"r","label":"unnamed-chunk-79"},"document_id":"933E5A60","chunk_id":"cgq8yox0kwywc","chunk_label":"unnamed-chunk-11"}],"doc_write_time":1644443714,"working_dir":null,"default_chunk_options":{}}